genflux/__init__.py
genflux/client.py
genflux-0.1.0.dist-info/METADATA
genflux-0.1.0.dist-info/WHEEL
genflux-0.1.0.dist-info/RECORD
